lemonGTM/__init__.py
lemon_gtm-1.0.0.dist-info/LICENSE
lemon_gtm-1.0.0.dist-info/METADATA
lemon_gtm-1.0.0.dist-info/WHEEL
lemon_gtm-1.0.0.dist-info/top_level.txt
lemon_gtm-1.0.0.dist-info/RECORD
