Metadata-Version: 2.1
Name: lemon-gtm
Version: 1.0.0
Summary: A Global Tracking Model for Python
Home-page: https://github.com/lemonorangeapple/lemon-gtm
Author: lemonorangeapple
Classifier: Programming Language :: Python :: 3
Classifier: License :: OSI Approved :: MIT License
Classifier: Operating System :: OS Independent
Requires-Python: >=3
License-File: LICENSE
Requires-Dist: jieba
